nonebot_plugin_ikun_evolution/.gitignore
nonebot_plugin_ikun_evolution/__init__.py
nonebot_plugin_ikun_evolution/gamedata/gamedata
nonebot_plugin_ikun_evolution/gamedata/image/item/IKUN图册.png
nonebot_plugin_ikun_evolution/gamedata/image/item/乌龟护符.png
nonebot_plugin_ikun_evolution/gamedata/image/item/大蟠桃.png
nonebot_plugin_ikun_evolution/gamedata/image/item/天织钥石.png
nonebot_plugin_ikun_evolution/gamedata/image/item/小沙漏.png
nonebot_plugin_ikun_evolution/gamedata/image/item/灵兽果实.png
nonebot_plugin_ikun_evolution/gamedata/image/notice/帮助.jpg
nonebot_plugin_ikun_evolution/gamedata/json/readme.md
nonebot_plugin_ikun_evolution/gamedata/notice/帮助.jpg
nonebot_plugin_ikun_evolution/gamedata/notice/旧帮助.jpg
nonebot_plugin_ikun_evolution/image_utils.py
nonebot_plugin_ikun_evolution/model/achievement_model.py
nonebot_plugin_ikun_evolution/model/adv_model.py
nonebot_plugin_ikun_evolution/model/battle_log_model.py
nonebot_plugin_ikun_evolution/model/mission_model.py
nonebot_plugin_ikun_evolution/model/other_model.py
nonebot_plugin_ikun_evolution/model/player_model.py
nonebot_plugin_ikun_evolution/psql_db/__init__.py
nonebot_plugin_ikun_evolution/psql_db/db_context.py
nonebot_plugin_ikun_evolution/service/achievement_handler.py
nonebot_plugin_ikun_evolution/service/adv_handler.py
nonebot_plugin_ikun_evolution/service/battle_handler.py
nonebot_plugin_ikun_evolution/service/equip_handler.py
nonebot_plugin_ikun_evolution/service/forge_handler.py
nonebot_plugin_ikun_evolution/service/game_handler.py
nonebot_plugin_ikun_evolution/service/help_handler.py
nonebot_plugin_ikun_evolution/service/look_handler.py
nonebot_plugin_ikun_evolution/service/mission_handler.py
nonebot_plugin_ikun_evolution/service/player_handler.py
nonebot_plugin_ikun_evolution/service/shop_handler.py
nonebot_plugin_ikun_evolution/service/skill_handler.py
nonebot_plugin_ikun_evolution/service/use_handler.py
nonebot_plugin_ikun_evolution/stream.py
nonebot_plugin_ikun_evolution/tar.py
nonebot_plugin_ikun_evolution-1.0.12.dist-info/WHEEL
nonebot_plugin_ikun_evolution-1.0.12.dist-info/METADATA
nonebot_plugin_ikun_evolution-1.0.12.dist-info/RECORD
