Metadata-Version: 2.1
Name: nonebot-plugin-ikun-evolution
Version: 1.0.12
Summary: 移植自真寻的q群小游戏
Home-page: https://github.com/RShock/nonebot_plugin_ikun_evolution
License: MIT
Keywords: nonebot,nonebot2
Author: 小r
Author-email: 418648118@qq.com
Requires-Python: >=3.9,<4.0
Classifier: License :: OSI Approved :: MIT License
Classifier: Programming Language :: Python :: 3
Classifier: Programming Language :: Python :: 3.9
Classifier: Programming Language :: Python :: 3.10
Classifier: Programming Language :: Python :: 3.11
Requires-Dist: gino (>=1.0.1,<2.0.0)
Requires-Dist: json5 (>=0.9.10,<0.10.0)
Requires-Dist: lagom (>=2.2.0,<3.0.0)
Requires-Dist: nonebot-adapter-onebot (>=2.0.0-beta.1,<3.0.0)
Requires-Dist: nonebot2 (>=2.0.0-beta.1,<3.0.0)
Requires-Dist: python-dateutil (>=2.7)
Project-URL: Repository, https://github.com/RShock/nonebot_plugin_ikun_evolution
